psan/__init__.py
psan/psan.py
psan_mr0rang3-1.0.dist-info/METADATA
psan_mr0rang3-1.0.dist-info/WHEEL
psan_mr0rang3-1.0.dist-info/top_level.txt
psan_mr0rang3-1.0.dist-info/RECORD
